sitez/__init__.py
sitez/__main__.py
sitez/cli.py
sitez-0.1.0.dist-info/entry_points.txt
sitez-0.1.0.dist-info/WHEEL
sitez-0.1.0.dist-info/METADATA
sitez-0.1.0.dist-info/RECORD
