Metadata-Version: 2.1
Name: sitez
Version: 0.1.0
Summary: another site generator
License: MIT
Author: duyixian
Author-email: duyixian1234@qq.com
Requires-Python: >=3.8,<4.0
Classifier: License :: OSI Approved :: MIT License
Classifier: Programming Language :: Python :: 3
Classifier: Programming Language :: Python :: 3.8
Classifier: Programming Language :: Python :: 3.9
Requires-Dist: html-dsl (>=0.4.0,<0.5.0)
Requires-Dist: pydantic (>=1.8.1,<2.0.0)
Requires-Dist: toml (>=0.10.2,<0.11.0)
Requires-Dist: typer (>=0.3.2,<0.4.0)
